slant/__init__.py
slant/bias.py
slant/content.py
slant/dictionaries/bias_words.txt
slant/dictionaries/emoji_utf8_lexicon.txt
slant/dictionaries/stop_words.txt
slant/dictionaries/vader_lexicon.txt
slant/sentiment.py
slant/utils.py
slant-0.1.5.dist-info/LICENSE.md
slant-0.1.5.dist-info/WHEEL
slant-0.1.5.dist-info/METADATA
slant-0.1.5.dist-info/RECORD
