Metadata-Version: 2.1
Name: slant
Version: 0.1.5
Summary: Identify and measure bias in Python
License: CC0 1.0 Universal
Author: William W. Marx
Author-email: null@marx.design
Requires-Python: >=3.6,<4.0
Classifier: License :: Other/Proprietary License
Classifier: Programming Language :: Python :: 3
Classifier: Programming Language :: Python :: 3.6
Classifier: Programming Language :: Python :: 3.7
Classifier: Programming Language :: Python :: 3.8
Classifier: Programming Language :: Python :: 3.9
Requires-Dist: multiprocess (>=0.70.12,<0.71.0)
Requires-Dist: numpy (>=1.19.5,<2.0.0)
